setup.py
dsnd_probability_tw/Binomialdistribution.py
dsnd_probability_tw/Gaussiandistribution.py
dsnd_probability_tw/Generaldistribution.py
dsnd_probability_tw/__init__.py
dsnd_probability_tw.egg-info/PKG-INFO
dsnd_probability_tw.egg-info/SOURCES.txt
dsnd_probability_tw.egg-info/dependency_links.txt
dsnd_probability_tw.egg-info/not-zip-safe
dsnd_probability_tw.egg-info/top_level.txt