Metadata-Version: 1.0
Name: dsnd-probability-tw
Version: 0.1
Summary: Gaussian distributions
Home-page: UNKNOWN
Author: Tanise Williams
Author-email: tanise.williams@icloud.com
License: UNKNOWN
Platform: UNKNOWN
